actronair_api/__init__.py
actronair_api/api.py
actronair_api/auth.py
actronair_api/const.py
actronair_api/exceptions.py
actronair_api/model.py
actronair_api-0.1.6.dist-info/licenses/LICENSE
tests/testValues.py
tests/test_api.py
actronair_api-0.1.6.dist-info/METADATA
actronair_api-0.1.6.dist-info/WHEEL
actronair_api-0.1.6.dist-info/top_level.txt
actronair_api-0.1.6.dist-info/RECORD
